pyanchor/__init__.py
pyanchor/cli.py
pyanchor/link_checker.py
pyanchor-0.8.1.dist-info/METADATA
pyanchor-0.8.1.dist-info/WHEEL
pyanchor-0.8.1.dist-info/entry_points.txt
pyanchor-0.8.1.dist-info/licenses/LICENSE
pyanchor-0.8.1.dist-info/RECORD
