Metadata-Version: 2.4
Name: pyanchor
Version: 0.8.1
Summary: Find your broken links, so users don't.
Project-URL: Homepage, https://github.com/EndlessTrax/pyanchor/
Project-URL: Documentation, https://github.com/EndlessTrax/pyanchor/blob/master/README.md
Project-URL: Repository, https://github.com/EndlessTrax/pyanchor.git
Project-URL: Issues, https://github.com/EndlessTrax/pyanchor/issues
Author-email: Ricky White <ricky@rickywhite.net>
License-File: LICENSE
Classifier: License :: OSI Approved :: MIT License
Classifier: Programming Language :: Python :: 3.8
Classifier: Programming Language :: Python :: 3.9
Classifier: Programming Language :: Python :: 3.10
Classifier: Programming Language :: Python :: 3.11
Classifier: Programming Language :: Python :: 3.12
Classifier: Programming Language :: Python :: 3.13
Requires-Python: >=3.8
Requires-Dist: beautifulsoup4>=4.12.3
Requires-Dist: colorama>=0.4.6
Requires-Dist: lxml>=5.3.0
Requires-Dist: requests>=2.32.3
Requires-Dist: typer>=0.12.5
